{
    "name": "Flexoki Dark",
    "semanticHighlighting": true,
    "colors": {
        "titleBar.activeBackground": "#100F0F",
        "titleBar.inactiveBackground": "#1C1B1A",
        "titleBar.border": "#282726",
        "titleBar.activeForeground": "#B7B5AC",
        "titleBar.inactiveForeground": "#878580",

        "editor.background": "#100F0F",
        "editor.foreground": "#E6E4D9",

        "statusBar.background": "#100F0F",
        "statusBar.noFolderBackground": "#100F0F",
        "statusBar.debuggingBackground": "#205EA640",

        "statusBar.border": "#282726",
        "statusBar.noFolderBorder": "#282726",
        "statusBar.debuggingBorder": "#282726",
        "statusBar.focusBorder": "#282726",

        "statusBar.foreground": "#B7B5AC",
        "statusBar.debuggingForeground": "#B7B5AC",
        "statusBar.noFolderForeground": "#B7B5AC",

        "sideBar.background": "#100F0F",
        "sideBar.border": "#282726",
        "sideBar.foreground": "#B7B5AC",

        "activityBar.background": "#100F0F",
        "activityBar.border": "#282726",
        "activityBar.activeBackground": "#282726",
        "activityBar.activeBorder": "#205EA6",
        "activityBar.activeFocusBorder": "#205EA6",
        "activityBar.dropBorder": "#205EA6",
        "activityBar.foreground": "#B7B5AC",
        "activityBar.inactiveForeground": "#878580",
        "activityBarBadge.background": "#205EA6",
        "activityBarBadge.foreground": "#FFFCF0",

        "commandCenter.background": "#100F0F",
        "commandCenter.border": "#282726",
        "commandCenter.foreground": "#878580",
        "commandCenter.inactiveForeground": "#878580",
        "commandCenter.inactiveBorder": "#282726",
        "commandCenter.activeBorder": "#282726",
        "commandCenter.activeBackground": "#282726",
        "commandCenter.activeForeground": "#B7B5AC",
        "commandCenter.debuggingBackground": "#205EA640",

        "quickInput.background": "#1C1B1A",
        "quickInput.foreground": "#878580",
        "quickInputList.focusBackground": "#205EA6",
        "quickInputList.focusForeground": "#FFFCF0",
        "quickInputList.focusIconForeground": "#FFFCF0",

        "input.background": "#1C1B1A",
        "input.border": "#282726",
        "input.foreground": "#B7B5AC",
        "input.placeholderForeground": "#878580",

        "menu.background": "#1C1B1A",
        "menu.border": "#282726",
        "menu.foreground": "#B7B5AC",
        "menu.selectionBackground": "#205EA6",
        "menu.selectionBorder": "#205EA600",
        "menu.selectionForeground": "#FFFCF0",
        "menu.separatorBackground": "#343331",

        "menubar.selectionBackground": "#205EA6",
        "menubar.selectionBorder": "#205EA600",
        "menubar.selectionForeground": "#FFFCF0",

        "terminal.background": "#1C1B1A",
        "terminal.ansiBlack": "#100F0F",
        "terminal.ansiBlue": "#205EA6",
        "terminal.ansiBrightBlack": "#575653",
        "terminal.ansiBrightBlue": "#4385BE",
        "terminal.ansiBrightCyan": "#3AA99F",
        "terminal.ansiBrightGreen": "#879A39",
        "terminal.ansiBrightMagenta": "#CE5D97",
        "terminal.ansiBrightRed": "#D14D41",
        "terminal.ansiBrightWhite": "#FFFCF0",
        "terminal.ansiBrightYellow": "#D0A215",
        "terminalCursor.foreground": "#E6E4D9",
        "terminal.ansiCyan": "#24837B",
        "terminal.ansiGreen": "#66800B",
        "terminal.ansiMagenta": "#A02F6F",
        "terminal.ansiRed": "#AF3029",
        "terminal.selectionBackground": "#DA702C",
        "terminal.ansiWhite": "#B7B5AC",
        "terminal.ansiYellow": "#C19C00"
    }
}
